knowledgegpt/__init__.py
knowledgegpt/extractors/__init__.py
knowledgegpt/extractors/audio_to_text_extractor.py
knowledgegpt/extractors/base_extractor.py
knowledgegpt/extractors/docs_extractor.py
knowledgegpt/extractors/helpers.py
knowledgegpt/extractors/hybrid_extractor.py
knowledgegpt/extractors/pdf_extractor.py
knowledgegpt/extractors/powerpoint_extractor.py
knowledgegpt/extractors/web_scrape_extractor.py
knowledgegpt/extractors/yt_audio_extractor.py
knowledgegpt/extractors/yt_subs_extractor.py
knowledgegpt/utils/__init__.py
knowledgegpt/utils/utils_completion.py
knowledgegpt/utils/utils_distance.py
knowledgegpt/utils/utils_docs.py
knowledgegpt/utils/utils_embedding.py
knowledgegpt/utils/utils_pdf.py
knowledgegpt/utils/utils_powerpoint.py
knowledgegpt/utils/utils_prompt.py
knowledgegpt/utils/utils_raw_whisper.py
knowledgegpt/utils/utils_scrape.py
knowledgegpt/utils/utils_subtitles.py
knowledgegpt/utils/utils_yt_playlist.py
knowledgegpt/utils/utils_yt_whisper.py
knowledgegpt-0.0.7b0.dist-info/LICENSE
knowledgegpt-0.0.7b0.dist-info/METADATA
knowledgegpt-0.0.7b0.dist-info/WHEEL
knowledgegpt-0.0.7b0.dist-info/top_level.txt
knowledgegpt-0.0.7b0.dist-info/RECORD
