Metadata-Version: 2.1
Name: knowledgegpt
Version: 0.0.7b0
Summary: A package for extracting and querying knowledge using GPT models
Home-page: https://github.com/geeks-of-data/knowled-gpt
Author: Eren Akbulut<erenakbulutwork@gmail.com>,Kaan Ozbudak<kaanozbudakk@gmail.com>
Author-email: erenakbulutwork@gmail.com,kaanozbudakk@gmail.com
Classifier: Programming Language :: Python :: 3
Classifier: License :: OSI Approved :: MIT License
Classifier: Operating System :: OS Independent
Requires-Python: >=3.7
License-File: LICENSE
Requires-Dist: fastapi
Requires-Dist: uvicorn
Requires-Dist: pandas
Requires-Dist: numpy
Requires-Dist: scikit-learn
Requires-Dist: transformers
Requires-Dist: python-docx
Requires-Dist: pdfminer.six
Requires-Dist: beautifulsoup4
Requires-Dist: requests
Requires-Dist: gdown
Requires-Dist: openai
Requires-Dist: spacy
Requires-Dist: sentence-transformers
Requires-Dist: yt-dlp
Requires-Dist: tiktoken
Requires-Dist: pydub
Requires-Dist: PyPDF2
Requires-Dist: python-pptx
Requires-Dist: faiss-cpu
Requires-Dist: cloudscraper
